{
  "fullName": "AWS::OpsWorks::App",
  "namespace": "AWS",
  "category": "OpsWorks",
  "name": "App",
  "description": "Defines an AWS OpsWorks app for an AWS OpsWorks stack. The app represents code that you want to run on an application server.",
  "properties": [
    {
      "name": "AppSource",
      "description": "Contains the information required to retrieve an app from a repository.",
      "typeDescription": "AWS OpsWorks Source Type",
      "required": false,
      "type": "OpsWorksSourceType",
      "update": "No interruption"
    },
    {
      "name": "Attributes",
      "description": "One or more user-defined key-value pairs to be added to the stack attributes bag.",
      "typeDescription": "A list of key-value pairs",
      "required": false,
      "type": "key[]",
      "update": "No interruption"
    },
    {
      "name": "Description",
      "description": "A description of the app.",
      "typeDescription": "String",
      "required": false,
      "type": "String",
      "update": "No interruption"
    },
    {
      "name": "Domains",
      "description": "The app virtual host settings, with multiple domains separated by commas. For example, 'www.example.com, example.com'.",
      "typeDescription": "List of strings",
      "required": false,
      "type": "String[]",
      "update": "No interruption"
    },
    {
      "name": "EnableSsl",
      "description": "Whether to enable SSL for this app.",
      "typeDescription": "Boolean",
      "required": false,
      "type": "Boolean",
      "update": "No interruption"
    },
    {
      "name": "Environment",
      "description": "The environment variables to associate with the AWS OpsWorks app.",
      "typeDescription": "List of AWS OpsWorks App Environment",
      "required": false,
      "type": "OpsWorksAppEnvironment[]",
      "update": "No interruption"
    },
    {
      "name": "Name",
      "description": "The AWS OpsWorks app name.",
      "typeDescription": "String",
      "required": true,
      "type": "String",
      "update": "No interruption"
    },
    {
      "name": "Shortname",
      "description": "The app short name, which is used internally by AWS OpsWorks and by Chef recipes.",
      "typeDescription": "String",
      "required": false,
      "type": "String",
      "update": "Replacement"
    },
    {
      "name": "SslConfiguration",
      "description": "The SSL configuration",
      "typeDescription": "AWS OpsWorks SslConfiguration Type",
      "required": false,
      "type": "OpsWorksSslConfigurationType",
      "update": "No interruption"
    },
    {
      "name": "StackId",
      "description": "The AWS OpsWorks stack ID that this app will be associated with.",
      "typeDescription": "String",
      "required": true,
      "type": "String",
      "update": "Replacement"
    },
    {
      "name": "Type",
      "description": "The app type. Each supported type is associated with a particular layer. For more information, see CreateApp in the AWS OpsWorks API Reference.",
      "typeDescription": "String",
      "required": true,
      "type": "String",
      "update": "No interruption"
    }
  ],
  "attributes": [],
  "referenceUrl": "http://docs.aws.amazon.com/AWSCloudFormation/latest/UserGuide/aws-resource-opsworks-app.html"
}